{
  "access": "public",
  "acls": null,
  "active": true,
  "annotation": null,
  "callable_by_client_api": false,
  "category": "1352af89db2d9340bea7ff561d9619f8",
  "copied_from": "09431639db7573000510196c29961943",
  "copied_from_name": "Add Recipient to Envelope Custom",
  "description": "&amp;amp;amp;lt;p&amp;amp;amp;gt;This action adds a recipient to an envelope on DocuSign. Prior to using this action, Create Draft Envelope from Template action will be used to generate a draft Envelope.&amp;amp;amp;lt;/p&amp;amp;amp;gt;\n\n&amp;amp;amp;lt;p&amp;amp;amp;gt;&amp;amp;amp;lt;b&amp;amp;amp;gt;Inputs:&amp;amp;amp;lt;/b&amp;amp;amp;gt;&amp;amp;amp;lt;/p&amp;amp;amp;gt;\n&amp;amp;amp;lt;ul&amp;amp;amp;gt;\n  &amp;amp;amp;lt;li&amp;amp;amp;gt;&amp;amp;amp;lt;b&amp;amp;amp;gt;Envelope&amp;amp;amp;lt;/b&amp;amp;amp;gt; - The envelope record that has the envelope ID.&amp;amp;amp;lt;/li&amp;amp;amp;gt;\n  &amp;amp;amp;lt;li&amp;amp;amp;gt;&amp;amp;amp;lt;b&amp;amp;amp;gt;Email&amp;amp;amp;lt;/b&amp;amp;amp;gt; - Email ID of the recipient.&amp;amp;amp;lt;/li&amp;amp;amp;gt;\n  &amp;amp;amp;lt;li&amp;amp;amp;gt;&amp;amp;amp;lt;b&amp;amp;amp;gt;Name&amp;amp;amp;lt;/b&amp;amp;amp;gt; - Name of the recipient.&amp;amp;amp;lt;/li&amp;amp;amp;gt;\n  &amp;amp;amp;lt;li&amp;amp;amp;gt;&amp;amp;amp;lt;b&amp;amp;amp;gt;Role Name&amp;amp;amp;lt;/b&amp;amp;amp;gt; - Role Name from the envelope to which the recipient is to be associated.&amp;amp;amp;lt;/li&amp;amp;amp;gt;\n  &amp;amp;amp;lt;li&amp;amp;amp;gt;&amp;amp;amp;lt;b&amp;amp;amp;gt;Recipient ID&amp;amp;amp;lt;/b&amp;amp;amp;gt; - Recipient ID from the envelope to which the recipient is to be associated.&amp;amp;amp;lt;/li&amp;amp;amp;gt;\n  &amp;amp;amp;lt;li&amp;amp;amp;gt;&amp;amp;amp;lt;b&amp;amp;amp;gt;Embedded Signing Recipient&amp;amp;amp;lt;/b&amp;amp;amp;gt; - Select or drag and drop the  ServiceNow user record to be used for embedded signing. The Email Address ,User Name and User ID fields are extracted from the user record and used for embedded signing. Ensure that the Use Embedded Signing checkbox is checked when using this field.&amp;amp;amp;lt;/li&amp;amp;amp;gt;\n&amp;amp;amp;lt;/ul&amp;amp;amp;gt;\n\n&amp;amp;amp;lt;p&amp;amp;amp;gt;&amp;amp;amp;lt;b&amp;amp;amp;gt;Outputs:&amp;amp;amp;lt;/b&amp;amp;amp;gt;&amp;amp;amp;lt;/p&amp;amp;amp;gt;\n&amp;amp;amp;lt;ul&amp;amp;amp;gt;\n  &amp;amp;amp;lt;li&amp;amp;amp;gt;&amp;amp;amp;lt;b&amp;amp;amp;gt;Status&amp;amp;amp;lt;/b&amp;amp;amp;gt; - Will be set to &amp;amp;amp;quot;Success&amp;amp;amp;quot; if the request succeeds or &amp;amp;amp;quot;Error&amp;amp;amp;quot; if a failure occurs.&amp;amp;amp;lt;/li&amp;amp;amp;gt;\n  &amp;amp;amp;lt;li&amp;amp;amp;gt;&amp;amp;amp;lt;b&amp;amp;amp;gt;Error Message&amp;amp;amp;lt;/b&amp;amp;amp;gt; - Will be populated when the status is &amp;amp;amp;quot;Error&amp;amp;amp;quot;.&amp;amp;amp;lt;/li&amp;amp;amp;gt;\n&amp;amp;amp;lt;/ul&amp;amp;amp;gt;\n\n&amp;amp;amp;lt;p&amp;amp;amp;gt;&amp;amp;amp;lt;b&amp;amp;amp;gt;Error Messages:&amp;amp;amp;lt;/b&amp;amp;amp;gt;&amp;amp;amp;lt;/p&amp;amp;amp;gt;\n&amp;amp;amp;lt;ul&amp;amp;amp;gt;\n  &amp;amp;amp;lt;li&amp;amp;amp;gt;The specified Integrator Key was not found or is disabled. Please verify the configured credentials.&amp;amp;amp;lt;/li&amp;amp;amp;gt;\n  &amp;amp;amp;lt;li&amp;amp;amp;gt;User lacks sufficient permission to perform this action.&amp;amp;amp;lt;/li&amp;amp;amp;gt;\n  &amp;amp;amp;lt;li&amp;amp;amp;gt;Provided recipient ID is invalid or does not exist.&amp;amp;amp;lt;/li&amp;amp;amp;gt;\n  &amp;amp;amp;lt;li&amp;amp;amp;gt;The email address for the recipient is invalid or is of incorrect format.&amp;amp;amp;lt;/li&amp;amp;amp;gt;\n  &amp;amp;amp;lt;li&amp;amp;amp;gt;User Record is not provided or the User Record is missing either the name, email or user ID.&amp;amp;amp;lt;/li&amp;amp;amp;gt;\n  &amp;amp;amp;lt;li&amp;amp;amp;gt;Either Email or Name has not been provided.&amp;amp;amp;lt;/li&amp;amp;amp;gt;\n&amp;amp;amp;lt;/ul&amp;amp;amp;gt;\n\n&amp;amp;amp;lt;p&amp;amp;amp;gt;To use this action, the corresponding DocuSign connection and credential must be created and associated with the DocuSign Connection &amp;amp;amp;amp; Credential alias.&amp;amp;amp;lt;/p&amp;amp;amp;gt;\n\n&amp;amp;amp;lt;p&amp;amp;amp;gt;&amp;amp;amp;lt;b&amp;amp;amp;gt;Additional Note:&amp;amp;amp;lt;/b&amp;amp;amp;gt;&amp;amp;amp;lt;/p&amp;amp;amp;gt;\n&amp;amp;amp;lt;ul&amp;amp;amp;gt;\n  &amp;amp;amp;lt;li&amp;amp;amp;gt;Requires a subscription to a DocuSign API Plan that satisfies your feature and transactions requirements. &amp;amp;amp;lt;a target=&amp;amp;amp;quot;_blank&amp;amp;amp;quot; href=&amp;amp;amp;quot;https://www.docusign.com/products-and-pricing/api-plans&amp;amp;amp;quot;&amp;amp;amp;gt;Read More&amp;amp;amp;lt;/a&amp;amp;amp;gt;.&amp;amp;amp;lt;/li&amp;amp;amp;gt;\n&amp;amp;amp;lt;/ul&amp;amp;amp;gt;\n&amp;amp;amp;lt;p&amp;amp;amp;gt;To use this action, the corresponding DocuSign connection and credential must be created and associated with the DocuSign Connection &amp;amp;amp;amp; Credential alias. &amp;amp;amp;lt;a target=&amp;amp;amp;quot;_blank&amp;amp;amp;quot; href=&amp;amp;amp;quot;http://docs.servicenow.com/?context=CSHelp:credentials-connections-alias&amp;amp;amp;quot;&amp;amp;amp;gt;Learn More&amp;amp;amp;lt;/a&amp;amp;amp;gt;&amp;amp;amp;lt;/p&amp;amp;amp;gt;\n\n&amp;amp;amp;lt;p&amp;amp;amp;gt;&amp;amp;amp;lt;b&amp;amp;amp;gt;Note&amp;amp;amp;lt;/b&amp;amp;amp;gt;: Requires a subscription for production use. &amp;amp;amp;lt;a target=&amp;amp;amp;quot;_blank&amp;amp;amp;quot; href=&amp;amp;amp;quot;https://docs.servicenow.com/?context=CSHelp:IntegrationHub-licensing-information&amp;amp;amp;quot;&amp;amp;amp;gt;Read More&amp;amp;amp;lt;/a&amp;amp;amp;gt;.&amp;amp;amp;lt;/p&amp;amp;amp;gt;\n",
  "internal_name": "add_recipient_to_envelope_custom_1",
  "label_cache": "[{\"name\":\"{{action.email}}\",\"label\":\"action➛Email\",\"type\":\"action\",\"ref\":\"\"},{\"name\":\"{{action.full_name}}\",\"label\":\"action➛Name\",\"type\":\"action\",\"ref\":\"\"},{\"name\":\"{{action.role_name}}\",\"label\":\"action➛Role Name\",\"type\":\"action\",\"ref\":\"\"},{\"name\":\"{{action.recipient_id}}\",\"label\":\"action➛Recipient ID\",\"type\":\"action\",\"ref\":\"\"},{\"name\":\"{{action.envelope}}\",\"label\":\"action➛Envelope\",\"type\":\"action\",\"ref\":\"\"},{\"name\":\"{{action.envelope.account.alias}}\",\"label\":\"action➛Envelope➛Account➛Alias\",\"type\":\"action\",\"ref\":\"sys_alias\"},{\"name\":\"{{action.envelope.account.id}}\",\"label\":\"action➛Envelope➛Account➛ID\",\"type\":\"action\",\"ref\":\"\"},{\"name\":\"{{action.envelope.id}}\",\"label\":\"action➛Envelope➛ID\",\"type\":\"action\",\"ref\":\"\"},{\"name\":\"{{action.envelope.embedded_signing}}\",\"label\":\"action➛Envelope➛Embedded Signing\",\"type\":\"action\",\"ref\":\"\"},{\"name\":\"{{action.embedded_signing_recipient}}\",\"label\":\"action➛Embedded Signing Recipient\",\"type\":\"action\",\"ref\":\"\"},{\"name\":\"{{action.embedded_signing_recipient.name}}\",\"label\":\"action➛Embedded Signing Recipient➛Name\",\"type\":\"action\",\"ref\":\"\"},{\"name\":\"{{action.embedded_signing_recipient.email}}\",\"label\":\"action➛Embedded Signing Recipient➛Email\",\"type\":\"action\",\"ref\":\"\"},{\"name\":\"{{action.embedded_signing_recipient.user_name}}\",\"label\":\"action➛Embedded Signing Recipient➛User ID\",\"type\":\"action\",\"ref\":\"\"},{\"name\":\"{{action.recipient_signature_provider}}\",\"label\":\"action➛Recipient Signature Provider\",\"type\":\"action\",\"ref\":\"\"},{\"name\":\"{{step[c08eac7d-da68-4686-ae6a-ab37c4ab2fdb].r}}\",\"label\":\"step➛Pre Processing➛r\",\"type\":\"step\",\"ref\":\"\"},{\"name\":\"{{step[c08eac7d-da68-4686-ae6a-ab37c4ab2fdb].re}}\",\"label\":\"step➛Pre Processing➛re\",\"type\":\"step\",\"ref\":\"\"},{\"name\":\"{{step[c08eac7d-da68-4686-ae6a-ab37c4ab2fdb].rec}}\",\"label\":\"step➛Pre Processing➛rec\",\"type\":\"step\",\"ref\":\"\"},{\"name\":\"{{step[c08eac7d-da68-4686-ae6a-ab37c4ab2fdb].reci}}\",\"label\":\"step➛Pre Processing➛reci\",\"type\":\"step\",\"ref\":\"\"},{\"name\":\"{{step[c08eac7d-da68-4686-ae6a-ab37c4ab2fdb].recip}}\",\"label\":\"step➛Pre Processing➛recip\",\"type\":\"step\",\"ref\":\"\"},{\"name\":\"{{step[c08eac7d-da68-4686-ae6a-ab37c4ab2fdb].recipi}}\",\"label\":\"step➛Pre Processing➛recipi\",\"type\":\"step\",\"ref\":\"\"},{\"name\":\"{{step[c08eac7d-da68-4686-ae6a-ab37c4ab2fdb].recipie}}\",\"label\":\"step➛Pre Processing➛recipie\",\"type\":\"step\",\"ref\":\"\"},{\"name\":\"{{step[c08eac7d-da68-4686-ae6a-ab37c4ab2fdb].recipien}}\",\"label\":\"step➛Pre Processing➛recipien\",\"type\":\"step\",\"ref\":\"\"},{\"name\":\"{{step[c08eac7d-da68-4686-ae6a-ab37c4ab2fdb].recipient}}\",\"label\":\"step➛Pre Processing➛recipient\",\"type\":\"step\",\"ref\":\"\"},{\"name\":\"{{step[8477b097-85db-49ae-877e-216115a47ef2].error_message}}\",\"label\":\"step➛Add Recipient to Envelope➛Error Message\",\"type\":\"step\",\"ref\":\"\"},{\"name\":\"{{step[8477b097-85db-49ae-877e-216115a47ef2].status_code}}\",\"label\":\"step➛Add Recipient to Envelope➛Status Code\",\"type\":\"step\",\"ref\":\"\"},{\"name\":\"{{step[8477b097-85db-49ae-877e-216115a47ef2].response_body}}\",\"label\":\"step➛Add Recipient to Envelope➛Response Body\",\"type\":\"step\",\"ref\":\"\"},{\"name\":\"{{step[f71ae726-c48f-4b1b-bd2c-353c5e7840b6].error_message}}\",\"label\":\"step➛Handle Errors➛error_message\",\"type\":\"step\",\"ref\":\"\"},{\"name\":\"{{step[c08eac7d-da68-4686-ae6a-ab37c4ab2fdb].pre_status}}\",\"label\":\"step➛Pre Processing➛pre_status\",\"type\":\"step\",\"ref\":\"\"}]",
  "latest_snapshot": null,
  "master_snapshot": null,
  "name": "Add Recipient to Envelope Custom 1",
  "outputs": null,
  "state": "draft",
  "sys_class_name": "sys_hub_action_type_definition",
  "sys_created_by": "admin",
  "sys_created_on": "2019-07-07 23:14:18",
  "sys_id": "0df5f738dba233000510196c299619d3",
  "sys_mod_count": 2,
  "sys_name": "Add Recipient to Envelope Custom 1",
  "sys_package": "209eafd9f56133007f447024bdae7fe1",
  "sys_policy": null,
  "sys_scope": "209eafd9f56133007f447024bdae7fe1",
  "sys_update_name": "sys_hub_action_type_definition_0df5f738dba233000510196c299619d3",
  "sys_updated_by": "admin",
  "sys_updated_on": "2019-07-07 23:14:22",
  "system_level": false,
  "type": null
}
